timeloop/__init__.py
timeloop/app.py
timeloop/exceptions.py
timeloop/helpers.py
timeloop/job.py
timeloop-1.0.2.dist-info/DESCRIPTION.rst
timeloop-1.0.2.dist-info/METADATA
timeloop-1.0.2.dist-info/RECORD
timeloop-1.0.2.dist-info/WHEEL
timeloop-1.0.2.dist-info/metadata.json
timeloop-1.0.2.dist-info/top_level.txt
