Metadata-Version: 2.0
Name: timeloop
Version: 1.0.2
Summary: An elegant way to run period tasks.
Home-page: https://github.com/sankalpjonn/timeloop
Author: Sankalp Jonna
Author-email: sankalpjonna@gmail.com
License: MIT
Keywords: tasks,jobs,periodic task,interval,periodic job,flask style,decorator
Platform: UNKNOWN
